funtalk/__init__.py
funtalk/asr/__init__.py
funtalk/asr/_whisper.py
funtalk/asr/base.py
funtalk/tts/__init__.py
funtalk/tts/_azure.py
funtalk/tts/_edge.py
funtalk/tts/base.py
funtalk-1.0.26.dist-info/METADATA
funtalk-1.0.26.dist-info/WHEEL
funtalk-1.0.26.dist-info/top_level.txt
funtalk-1.0.26.dist-info/RECORD
