Metadata-Version: 2.1
Name: funtalk
Version: 1.0.26
Summary: funtalk
Author-email: niuliangtao <farfarfun@qq.com>
Requires-Python: >=3.8
